{
  "annotations": {
    "list": [
      {
        "builtIn": 1,
        "datasource": "-- Grafana --",
        "enable": true,
        "hide": true,
        "iconColor": "rgba(0, 211, 255, 1)",
        "name": "Annotations & Alerts",
        "type": "dashboard"
      }
    ]
  },
  "editable": true,
  "gnetId": null,
  "graphTooltip": 0,
  "id": null,
  "links": [],
  "panels": [
    {
      "datasource": null,
      "fieldConfig": {
        "defaults": {},
        "overrides": []
      },
      "gridPos": {
        "h": 3,
        "w": 24,
        "x": 0,
        "y": 0
      },
      "id": 2,
      "options": {
        "content": "# 🔍 GatewayZ Backend Monitoring Dashboard\n\nReal-time provider health, analytics, and anomaly detection system. Monitor 17+ providers with comprehensive performance metrics, cost analysis, and automated anomaly detection.\n\n**Features:**\n- 📊 Real-time health scores (0-100) for all providers\n- ⚠️ Automatic anomaly detection with severity levels\n- 💰 Cost breakdown and analysis\n- 📈 Time-series performance trends\n- 🔴 Critical alert indicators\n\n**Documentation:** See MONITORING_GUIDE.md for complete endpoint specifications and testing procedures.",
        "mode": "markdown"
      },
      "pluginVersion": "8.0.0",
      "targets": [],
      "title": "Header",
      "type": "text"
    },
    {
      "datasource": null,
      "fieldConfig": {
        "defaults": {},
        "overrides": []
      },
      "gridPos": {
        "h": 50,
        "w": 24,
        "x": 0,
        "y": 3
      },
      "id": 3,
      "options": {
        "folderId": null,
        "maxItems": 30,
        "query": "",
        "showHeadings": false,
        "showSearch": false,
        "showStarred": true,
        "tags": []
      },
      "pluginVersion": "8.0.0",
      "targets": [],
      "title": "🔍 Interactive Monitoring Tool",
      "type": "stat"
    },
    {
      "datasource": null,
      "fieldConfig": {
        "defaults": {
          "color": {
            "mode": "palette-classic"
          },
          "custom": {
            "hideFrom": {
              "tooltip": false,
              "viz": false,
              "legend": false
            }
          },
          "mappings": []
        },
        "overrides": []
      },
      "gridPos": {
        "h": 8,
        "w": 24,
        "x": 0,
        "y": 53
      },
      "id": 4,
      "options": {
        "legend": {
          "calcs": [],
          "displayMode": "list",
          "placement": "bottom"
        },
        "pieType": "donut",
        "tooltip": {
          "mode": "single"
        }
      },
      "pluginVersion": "8.0.0",
      "targets": [
        {
          "refId": "A"
        }
      ],
      "title": "💰 Cost Breakdown by Provider (24h)",
      "type": "piechart"
    },
    {
      "datasource": null,
      "fieldConfig": {
        "defaults": {
          "color": {
            "mode": "thresholds"
          },
          "mappings": [],
          "thresholds": {
            "mode": "absolute",
            "steps": [
              {
                "color": "green",
                "value": null
              },
              {
                "color": "yellow",
                "value": 50
              },
              {
                "color": "red",
                "value": 80
              }
            ]
          }
        },
        "overrides": []
      },
      "gridPos": {
        "h": 8,
        "w": 12,
        "x": 0,
        "y": 61
      },
      "id": 5,
      "options": {
        "orientation": "auto",
        "showThresholdLabels": false,
        "showThresholdMarkers": true
      },
      "pluginVersion": "8.0.0",
      "targets": [
        {
          "refId": "A"
        }
      ],
      "title": "📊 Average Response Latency (p95)",
      "type": "gauge"
    },
    {
      "datasource": null,
      "fieldConfig": {
        "defaults": {
          "color": {
            "mode": "thresholds"
          },
          "mappings": [],
          "thresholds": {
            "mode": "absolute",
            "steps": [
              {
                "color": "green",
                "value": null
              },
              {
                "color": "yellow",
                "value": 5
              },
              {
                "color": "red",
                "value": 10
              }
            ]
          }
        },
        "overrides": []
      },
      "gridPos": {
        "h": 8,
        "w": 12,
        "x": 12,
        "y": 61
      },
      "id": 6,
      "options": {
        "orientation": "auto",
        "showThresholdLabels": false,
        "showThresholdMarkers": true
      },
      "pluginVersion": "8.0.0",
      "targets": [
        {
          "refId": "A"
        }
      ],
      "title": "🔴 Error Rate Percentage (24h)",
      "type": "gauge"
    },
    {
      "datasource": null,
      "fieldConfig": {
        "defaults": {
          "color": {
            "mode": "palette-classic"
          },
          "custom": {
            "axisCenteredZero": false,
            "axisColorMode": "text",
            "axisLabel": "Requests",
            "axisPlacement": "auto",
            "barAlignment": 0,
            "drawStyle": "line",
            "fillOpacity": 10,
            "gradientMode": "none",
            "hideFrom": {
              "tooltip": false,
              "viz": false,
              "legend": false
            },
            "lineInterpolation": "linear",
            "lineWidth": 1,
            "pointSize": 5,
            "scaleDistribution": {
              "type": "linear"
            },
            "showPoints": "auto",
            "spanNulls": true,
            "stacking": {
              "group": "A",
              "mode": "none"
            },
            "thresholdsStyle": {
              "mode": "off"
            }
          },
          "mappings": [],
          "thresholds": {
            "mode": "absolute",
            "steps": [
              {
                "color": "green",
                "value": null
              }
            ]
          }
        },
        "overrides": []
      },
      "gridPos": {
        "h": 8,
        "w": 24,
        "x": 0,
        "y": 69
      },
      "id": 7,
      "options": {
        "legend": {
          "calcs": [],
          "displayMode": "list",
          "placement": "bottom"
        },
        "tooltip": {
          "mode": "single"
        }
      },
      "pluginVersion": "8.0.0",
      "targets": [
        {
          "refId": "A"
        }
      ],
      "title": "📈 Request Volume Trends (Top 5 Providers)",
      "type": "timeseries"
    },
    {
      "datasource": null,
      "fieldConfig": {
        "defaults": {
          "color": {
            "mode": "palette-classic"
          },
          "custom": {
            "axisCenteredZero": false,
            "axisColorMode": "text",
            "axisLabel": "Latency (ms)",
            "axisPlacement": "auto",
            "barAlignment": 0,
            "drawStyle": "line",
            "fillOpacity": 10,
            "gradientMode": "none",
            "hideFrom": {
              "tooltip": false,
              "viz": false,
              "legend": false
            },
            "lineInterpolation": "linear",
            "lineWidth": 1,
            "pointSize": 5,
            "scaleDistribution": {
              "type": "linear"
            },
            "showPoints": "auto",
            "spanNulls": true,
            "stacking": {
              "group": "A",
              "mode": "none"
            },
            "thresholdsStyle": {
              "mode": "off"
            }
          },
          "mappings": [],
          "thresholds": {
            "mode": "absolute",
            "steps": [
              {
                "color": "green",
                "value": null
              }
            ]
          }
        },
        "overrides": []
      },
      "gridPos": {
        "h": 8,
        "w": 24,
        "x": 0,
        "y": 77
      },
      "id": 8,
      "options": {
        "legend": {
          "calcs": [],
          "displayMode": "list",
          "placement": "bottom"
        },
        "tooltip": {
          "mode": "single"
        }
      },
      "pluginVersion": "8.0.0",
      "targets": [
        {
          "refId": "A"
        }
      ],
      "title": "⏱️ Latency Trends (p95 Percentile)",
      "type": "timeseries"
    },
    {
      "datasource": null,
      "fieldConfig": {
        "defaults": {
          "color": {
            "mode": "palette-classic"
          },
          "custom": {
            "axisCenteredZero": false,
            "axisColorMode": "text",
            "axisLabel": "Errors",
            "axisPlacement": "auto",
            "barAlignment": 0,
            "drawStyle": "line",
            "fillOpacity": 10,
            "gradientMode": "none",
            "hideFrom": {
              "tooltip": false,
              "viz": false,
              "legend": false
            },
            "lineInterpolation": "linear",
            "lineWidth": 1,
            "pointSize": 5,
            "scaleDistribution": {
              "type": "linear"
            },
            "showPoints": "auto",
            "spanNulls": true,
            "stacking": {
              "group": "A",
              "mode": "none"
            },
            "thresholdsStyle": {
              "mode": "off"
            }
          },
          "mappings": [],
          "thresholds": {
            "mode": "absolute",
            "steps": [
              {
                "color": "green",
                "value": null
              }
            ]
          }
        },
        "overrides": []
      },
      "gridPos": {
        "h": 8,
        "w": 24,
        "x": 0,
        "y": 85
      },
      "id": 9,
      "options": {
        "legend": {
          "calcs": [],
          "displayMode": "list",
          "placement": "bottom"
        },
        "tooltip": {
          "mode": "single"
        }
      },
      "pluginVersion": "8.0.0",
      "targets": [
        {
          "refId": "A"
        }
      ],
      "title": "🔴 Error Rate Trends",
      "type": "timeseries"
    },
    {
      "datasource": null,
      "fieldConfig": {
        "defaults": {
          "color": {
            "mode": "palette-classic"
          },
          "custom": {
            "axisCenteredZero": false,
            "axisColorMode": "text",
            "axisLabel": "Cost ($)",
            "axisPlacement": "auto",
            "barAlignment": 0,
            "drawStyle": "line",
            "fillOpacity": 10,
            "gradientMode": "none",
            "hideFrom": {
              "tooltip": false,
              "viz": false,
              "legend": false
            },
            "lineInterpolation": "linear",
            "lineWidth": 1,
            "pointSize": 5,
            "scaleDistribution": {
              "type": "linear"
            },
            "showPoints": "auto",
            "spanNulls": true,
            "stacking": {
              "group": "A",
              "mode": "none"
            },
            "thresholdsStyle": {
              "mode": "off"
            }
          },
          "mappings": [],
          "thresholds": {
            "mode": "absolute",
            "steps": [
              {
                "color": "green",
                "value": null
              }
            ]
          }
        },
        "overrides": []
      },
      "gridPos": {
        "h": 8,
        "w": 24,
        "x": 0,
        "y": 93
      },
      "id": 10,
      "options": {
        "legend": {
          "calcs": [],
          "displayMode": "list",
          "placement": "bottom"
        },
        "tooltip": {
          "mode": "single"
        }
      },
      "pluginVersion": "8.0.0",
      "targets": [
        {
          "refId": "A"
        }
      ],
      "title": "💰 Cost Trends Over Time",
      "type": "timeseries"
    },
    {
      "datasource": null,
      "fieldConfig": {
        "defaults": {
          "color": {
            "mode": "palette-classic"
          },
          "custom": {
            "displayMode": "auto",
            "filterable": false
          },
          "mappings": [],
          "thresholds": {
            "mode": "absolute",
            "steps": [
              {
                "color": "green",
                "value": null
              }
            ]
          }
        },
        "overrides": [
          {
            "matcher": {
              "id": "byName",
              "options": "Severity"
            },
            "properties": [
              {
                "id": "custom.displayMode",
                "value": "color-background"
              },
              {
                "id": "color",
                "value": {
                  "mode": "value"
                }
              },
              {
                "id": "mappings",
                "value": [
                  {
                    "options": {
                      "CRITICAL": {
                        "color": "dark-red",
                        "index": 0
                      },
                      "WARNING": {
                        "color": "dark-yellow",
                        "index": 1
                      }
                    },
                    "type": "value"
                  }
                ]
              }
            ]
          }
        ]
      },
      "gridPos": {
        "h": 10,
        "w": 24,
        "x": 0,
        "y": 101
      },
      "id": 11,
      "options": {
        "footer": {
          "countRows": false,
          "fields": "",
          "reducer": [
            "sum"
          ],
          "show": false
        },
        "showHeader": true
      },
      "pluginVersion": "8.0.0",
      "targets": [
        {
          "refId": "A"
        }
      ],
      "title": "⚠️ Active Anomalies & Alerts",
      "type": "table"
    },
    {
      "datasource": null,
      "fieldConfig": {
        "defaults": {
          "color": {
            "mode": "palette-classic"
          },
          "custom": {
            "displayMode": "auto",
            "filterable": false
          },
          "mappings": [],
          "thresholds": {
            "mode": "absolute",
            "steps": [
              {
                "color": "green",
                "value": null
              }
            ]
          }
        },
        "overrides": [
          {
            "matcher": {
              "id": "byName",
              "options": "Health Score"
            },
            "properties": [
              {
                "id": "custom.displayMode",
                "value": "color-background"
              },
              {
                "id": "color",
                "value": {
                  "mode": "value"
                }
              },
              {
                "id": "mappings",
                "value": [
                  {
                    "type": "range",
                    "options": {
                      "from": 0,
                      "to": 50,
                      "result": {
                        "color": "dark-red",
                        "index": 0
                      }
                    }
                  },
                  {
                    "type": "range",
                    "options": {
                      "from": 50,
                      "to": 80,
                      "result": {
                        "color": "dark-yellow",
                        "index": 1
                      }
                    }
                  },
                  {
                    "type": "range",
                    "options": {
                      "from": 80,
                      "to": 100,
                      "result": {
                        "color": "dark-green",
                        "index": 2
                      }
                    }
                  }
                ]
              }
            ]
          }
        ]
      },
      "gridPos": {
        "h": 10,
        "w": 24,
        "x": 0,
        "y": 111
      },
      "id": 12,
      "options": {
        "footer": {
          "countRows": false,
          "fields": "",
          "reducer": [
            "sum"
          ],
          "show": false
        },
        "showHeader": true
      },
      "pluginVersion": "8.0.0",
      "targets": [
        {
          "refId": "A"
        }
      ],
      "title": "📊 Provider Health Summary",
      "type": "table"
    }
  ],
  "refresh": "30s",
  "schemaVersion": 27,
  "style": "dark",
  "tags": [
    "monitoring",
    "providers",
    "gatewayz",
    "anomaly-detection"
  ],
  "templating": {
    "list": [
      {
        "allValue": null,
        "current": {
          "selected": false,
          "text": "https://api.gatewayz.ai",
          "value": "https://api.gatewayz.ai"
        },
        "datasource": null,
        "definition": "",
        "description": null,
        "error": null,
        "errorOnNew": false,
        "hide": 0,
        "includeAll": false,
        "label": "API Base URL",
        "multi": false,
        "name": "api_base_url",
        "options": [],
        "query": "",
        "refresh": 1,
        "regex": "",
        "skipUrlSync": false,
        "sort": 0,
        "tagValuesQuery": "",
        "tagsQuery": "",
        "tagsQuery": "",
        "text": "https://api.gatewayz.ai",
        "type": "custom",
        "useTags": false
      },
      {
        "current": {
          "selected": false,
          "text": "1d",
          "value": "1d"
        },
        "datasource": null,
        "definition": "",
        "description": null,
        "error": null,
        "errorOnNew": false,
        "hide": 0,
        "includeAll": false,
        "label": "Time Range",
        "multi": false,
        "name": "time_range",
        "options": [
          {
            "selected": false,
            "text": "1h",
            "value": "1h"
          },
          {
            "selected": true,
            "text": "1d",
            "value": "1d"
          },
          {
            "selected": false,
            "text": "1w",
            "value": "1w"
          },
          {
            "selected": false,
            "text": "1m",
            "value": "1m"
          },
          {
            "selected": false,
            "text": "1y",
            "value": "1y"
          }
        ],
        "query": "1h,1d,1w,1m,1y",
        "skipUrlSync": false,
        "sort": 0,
        "tagValuesQuery": "",
        "tagsQuery": "",
        "type": "custom"
      }
    ]
  },
  "time": {
    "from": "now-24h",
    "to": "now"
  },
  "timepicker": {},
  "timezone": "",
  "title": "GatewayZ Backend Monitoring",
  "uid": "gatewayz-monitoring-v1",
  "version": 0
}
